{
  "db_name": "PostgreSQL",
  "query": "\n            SELECT p.pipeline_id, p.pipeline_name, p.description, p.project_id, p.created_at,\n                ARRAY(\n                    SELECT (s.step_id, s.step_definition_id, s.pipeline_id, s.step_parameters)\n                    FROM \"steps\" s WHERE s.pipeline_id = $1\n                ) as \"steps: Vec<Step>\"\n            FROM \"pipelines\" p\n            WHERE p.pipeline_id = $1\n            GROUP BY p.pipeline_id\n        ",
  "describe": {
    "columns": [
      {
        "ordinal": 0,
        "name": "pipeline_id",
        "type_info": "Uuid"
      },
      {
        "ordinal": 1,
        "name": "pipeline_name",
        "type_info": "Text"
      },
      {
        "ordinal": 2,
        "name": "description",
        "type_info": "Text"
      },
      {
        "ordinal": 3,
        "name": "project_id",
        "type_info": "Uuid"
      },
      {
        "ordinal": 4,
        "name": "created_at",
        "type_info": "Timestamptz"
      },
      {
        "ordinal": 5,
        "name": "steps: Vec<Step>",
        "type_info": "RecordArray"
      }
    ],
    "parameters": {
      "Left": [
        "Uuid"
      ]
    },
    "nullable": [
      false,
      false,
      true,
      false,
      false,
      null
    ]
  },
  "hash": "925ac6c1da599d0f85982cd3887fd65ad5b3b441603feaf7335779d27e61b5c1"
}
